setup.py
pygamedev/__init__.py
pygamedev/main.py
pygamedev.egg-info/PKG-INFO
pygamedev.egg-info/SOURCES.txt
pygamedev.egg-info/dependency_links.txt
pygamedev.egg-info/requires.txt
pygamedev.egg-info/top_level.txt