Metadata-Version: 2.1
Name: pygamedev
Version: 0.0.3
Summary: a package to make games
Home-page: UNKNOWN
Author: jortpower2009 (Jort Vlaming)
Author-email: <vlamingjort@gmail.com>
License: UNKNOWN
Keywords: python,game,dev,gamedev
Platform: UNKNOWN
